borsdata/__init__.py
borsdata/apiclient.py
borsdata/constants.py
borsdata/models/__init__.py
borsdata/models/branchesrespv1.py
borsdata/models/branchv1.py
borsdata/models/countriesrespv1.py
borsdata/models/countryv1.py
borsdata/models/instrumentsrespv1.py
borsdata/models/instrumentupdatedrespv1.py
borsdata/models/instrumentupdatedv1.py
borsdata/models/instrumentv1.py
borsdata/models/kpihistoryv1.py
borsdata/models/kpimetadatarespv1.py
borsdata/models/kpimetadatav1.py
borsdata/models/kpisallcomprespv1.py
borsdata/models/kpiscalcupdatedrespv1.py
borsdata/models/kpishistoryrespv1.py
borsdata/models/kpisrespv1.py
borsdata/models/kpissummaryrespv1.py
borsdata/models/kpisummarygroupv1.py
borsdata/models/kpisummaryvaluev1.py
borsdata/models/kpiv1.py
borsdata/models/marketsrespv1.py
borsdata/models/marketv1.py
borsdata/models/reportmetadatarespv1.py
borsdata/models/reportmetadatav1.py
borsdata/models/reportscompoundrespv1.py
borsdata/models/reportsrespv1.py
borsdata/models/reportv1.py
borsdata/models/sectorsrespv1.py
borsdata/models/sectorv1.py
borsdata/models/stockpricedatev1.py
borsdata/models/stockpricefullv1.py
borsdata/models/stockpricesdaterespv1.py
borsdata/models/stockpriceslastrespv1.py
borsdata/models/stockpricesrespv1.py
borsdata/models/stockpricev1.py
borsdata/models/stocksplitrespv1.py
borsdata/models/stocksplitv1.py
borsdata/models/translationmetadatarespv1.py
borsdata/models/translationmetadatav1.py
borsdata_apiclient-1.0.4.dist-info/LICENSE
borsdata_apiclient-1.0.4.dist-info/METADATA
borsdata_apiclient-1.0.4.dist-info/WHEEL
borsdata_apiclient-1.0.4.dist-info/top_level.txt
borsdata_apiclient-1.0.4.dist-info/RECORD
