Metadata-Version: 2.1
Name: borsdata-apiclient
Version: 1.0.4
Summary: API Client for borsdata.se.
Home-page: https://github.com/rahmnstein/borsdata-apiclient
Author: rahmnstein
Author-email: rahmnstein@gmail.com
License: MIT
Project-URL: Bug Tracker, https://github.com/rahmnstein/borsdata-apiclient/issues
Platform: any
Classifier: Programming Language :: Python :: 3
Classifier: License :: OSI Approved :: MIT License
Classifier: Operating System :: OS Independent
Requires-Python: >=3.6
License-File: LICENSE
Requires-Dist: requests
Requires-Dist: dataclasses-json
Requires-Dist: python-decouple
